pnne_search/__init__.py
pnne_search/curve.csv
pnne_search/data.npz
pnne_search/data_checks.py
pnne_search/masked_mse.py
pnne_search/moments.py
pnne_search/nne_info.json
pnne_search/nne_matlab.keras
pnne_search/pnne_estimate.py
pnne_search/predict_tree.py
pnne_search/tree_matlab.pkl
pnne_search/utils.py
pnne_search-0.1.2.dist-info/METADATA
pnne_search-0.1.2.dist-info/WHEEL
pnne_search-0.1.2.dist-info/top_level.txt
pnne_search-0.1.2.dist-info/RECORD
