Metadata-Version: 2.4
Name: pnne_search
Version: 0.1.2
Summary: A package for search model estimation
Home-page: https://pnnehome.github.io/
Classifier: Programming Language :: Python :: 3
Classifier: Operating System :: OS Independent
Requires-Python: >=3.6
Requires-Dist: tensorflow>=2.0.0
Requires-Dist: numpy>=1.15
Requires-Dist: scipy>=1.0.0
Requires-Dist: pandas>=1.0.0
Requires-Dist: joblib>=0.14.0
Requires-Dist: absl-py>=0.13.0
Dynamic: classifier
Dynamic: description
Dynamic: description-content-type
Dynamic: home-page
Dynamic: requires-dist
Dynamic: requires-python
Dynamic: summary
